[
  {
        "location": [
            93.28801475674513,
            43.56124820984395
        ],
        "population": 1000
    },
    {
        "location": [
            93.16048620934572,
            43.57924850261235
        ],
        "population": 1000
    },
    {
        "location": [
            93.02228718644082,
            43.584322033086224
        ],
        "population": 1000
    },
    {
        "location": [
            92.88415678540396,
            43.595074731578634
        ],
        "population": 1000
    },
    {
        "location": [
            92.7460263843671,
            43.60582743007104
        ],
        "population": 1000
    },
    {
        "location": [
            92.6079121949639,
            43.616662260635316
        ],
        "population": 1000
    },
    {
        "location": [
            92.47143209383655,
            43.63577577912371
        ],
        "population": 1000
    },
    {
        "location": [
            92.34633398514,
            43.67774690319771
        ],
        "population": 1000
    },
    {
        "location": [
            92.22580470626986,
            43.72811387549221
        ],
        "population": 1000
    },
    {
        "location": [
            92.10078070744912,
            43.76919595019514
        ],
        "population": 1000
    },
    {
        "location": [
            91.96430567799266,
            43.786527690412846
        ],
        "population": 1000
    },
    {
        "location": [
            91.82501282303366,
            43.78348141201076
        ],
        "population": 1000
    },
    {
        "location": [
            91.6861668946826,
            43.775151887162394
        ],
        "population": 1000
    },
    {
        "location": [
            91.54955948532528,
            43.757129941281036
        ],
        "population": 1000
    },
    {
        "location": [
            91.41636557500055,
            43.728871396750435
        ],
        "population": 1000
    },
    {
        "location": [
            91.28521934794334,
            43.713673528022866
        ],
        "population": 1000
    },
    {
        "location": [
            91.15740085198412,
            43.752969251098506
        ],
        "population": 1000
    },
    {
        "location": [
            91.01987788780312,
            43.769069385041455
        ],
        "population": 1000
    },
    {
        "location": [
            90.88590807327427,
            43.76364224973445
        ],
        "population": 1000
    },
    {
        "location": [
            90.75112308239474,
            43.78897047112751
        ],
        "population": 1000
    },
    {
        "location": [
            90.61412650419344,
            43.79065722647363
        ],
        "population": 1000
    },
    {
        "location": [
            90.47565037273921,
            43.7832131
        ],
        "population": 1000
    },
    {
        "location": [
            90.33629859834268,
            43.7832131
        ],
        "population": 1000
    },
    {
        "location": [
            90.19699826354011,
            43.78241836284531
        ],
        "population": 1000
    },
    {
        "location": [
            90.09161505299633,
            43.82377685765605
        ],
        "population": 1000
    },
    {
        "location": [
            90.01790157293188,
            43.90122050216733
        ],
        "population": 1000
    },
    {
        "location": [
            89.93743624108299,
            43.96124314535781
        ],
        "population": 1000
    },
    {
        "location": [
            89.79828615267557,
            43.96410420416317
        ],
        "population": 1000
    },
    {
        "location": [
            89.66166136998542,
            43.971849513406575
        ],
        "population": 1000
    },
    {
        "location": [
            89.56915381670127,
            44.03164785280734
        ],
        "population": 1000
    },
    {
        "location": [
            89.48078185361891,
            44.10831533090199
        ],
        "population": 1000
    },
    {
        "location": [
            89.41049432164878,
            44.19128885300504
        ],
        "population": 1000
    },
    {
        "location": [
            89.28470921127463,
            44.2350150094644
        ],
        "population": 1000
    },
    {
        "location": [
            89.15157275128354,
            44.26608673577168
        ],
        "population": 1000
    },
    {
        "location": [
            89.01149107966627,
            44.265849957032636
        ],
        "population": 1000
    },
    {
        "location": [
            88.8712903328529,
            44.26137296014546
        ],
        "population": 1000
    },
    {
        "location": [
            88.73391918259958,
            44.24202327381654
        ],
        "population": 1000
    },
    {
        "location": [
            88.59416456376086,
            44.23253203797069
        ],
        "population": 1000
    },
    {
        "location": [
            88.45560145241772,
            44.2177215583666
        ],
        "population": 1000
    },
    {
        "location": [
            88.31797945865162,
            44.19791650546893
        ],
        "population": 1000
    },
    {
        "location": [
            88.18106079263785,
            44.17594807189153
        ],
        "population": 1000
    },
    {
        "location": [
            88.04602883196107,
            44.148935865525125
        ],
        "population": 1000
    },
    {
        "location": [
            87.90711357794247,
            44.13673336751285
        ],
        "population": 1000
    },
    {
        "location": [
            87.76824730193158,
            44.12435439570684
        ],
        "population": 1000
    },
    {
        "location": [
            87.67185274610955,
            44.06172590451272
        ],
        "population": 1000
    },
    {
        "location": [
            87.59653027590991,
            43.98888911055917
        ],
        "population": 1000
    },
    {
        "location": [
            87.47426252178084,
            43.941070453955376
        ],
        "population": 1000
    },
    {
        "location": [
            87.35126539362227,
            43.97121660096741
        ],
        "population": 1000
    }
]