[
  {
        "location": [
            60.686517331216635,
            40.016821473840736
        ],
        "population": 1000
    },
    {
        "location": [
            60.55883012634593,
            40.040763125522915
        ],
        "population": 1000
    },
    {
        "location": [
            60.43117954889098,
            40.06516659361327
        ],
        "population": 1000
    },
    {
        "location": [
            60.30352897143603,
            40.08957006170363
        ],
        "population": 1000
    },
    {
        "location": [
            60.17587839398109,
            40.11397352979399
        ],
        "population": 1000
    },
    {
        "location": [
            60.048227816526136,
            40.13837699788434
        ],
        "population": 1000
    },
    {
        "location": [
            59.920577239071186,
            40.1627804659747
        ],
        "population": 1000
    },
    {
        "location": [
            59.80068447478282,
            40.204806449036425
        ],
        "population": 1000
    },
    {
        "location": [
            59.68086184212801,
            40.246991741910804
        ],
        "population": 1000
    },
    {
        "location": [
            59.5610392094732,
            40.28917703478519
        ],
        "population": 1000
    },
    {
        "location": [
            59.44121657681839,
            40.33136232765957
        ],
        "population": 1000
    },
    {
        "location": [
            59.32200457223102,
            40.37464675580484
        ],
        "population": 1000
    },
    {
        "location": [
            59.204917100036475,
            40.42175535878191
        ],
        "population": 1000
    },
    {
        "location": [
            59.08782962784193,
            40.46886396175897
        ],
        "population": 1000
    },
    {
        "location": [
            58.97074215564738,
            40.51597256473604
        ],
        "population": 1000
    },
    {
        "location": [
            58.85365468345284,
            40.5630811677131
        ],
        "population": 1000
    },
    {
        "location": [
            58.73656721125829,
            40.61018977069016
        ],
        "population": 1000
    },
    {
        "location": [
            58.61947973906374,
            40.65729837366723
        ],
        "population": 1000
    },
    {
        "location": [
            58.49386809444967,
            40.68907252613524
        ],
        "population": 1000
    },
    {
        "location": [
            58.36666657432874,
            40.71798659247694
        ],
        "population": 1000
    },
    {
        "location": [
            58.23946505420781,
            40.74690065881863
        ],
        "population": 1000
    },
    {
        "location": [
            58.113272733732614,
            40.7783070523802
        ],
        "population": 1000
    },
    {
        "location": [
            57.98867206571342,
            40.813644203109085
        ],
        "population": 1000
    },
    {
        "location": [
            57.86407139769424,
            40.84898135383797
        ],
        "population": 1000
    },
    {
        "location": [
            57.739470729675055,
            40.884318504566856
        ],
        "population": 1000
    },
    {
        "location": [
            57.614652169867355,
            40.919282723360936
        ],
        "population": 1000
    },
    {
        "location": [
            57.488652566980484,
            40.95222553196967
        ],
        "population": 1000
    },
    {
        "location": [
            57.36265296409361,
            40.9851683405784
        ],
        "population": 1000
    },
    {
        "location": [
            57.23665336120675,
            41.01811114918713
        ],
        "population": 1000
    },
    {
        "location": [
            57.11648747774563,
            41.0575112650427
        ],
        "population": 1000
    },
    {
        "location": [
            57.030758777611894,
            41.13502968197382
        ],
        "population": 1000
    },
    {
        "location": [
            56.945030077478165,
            41.21254809890493
        ],
        "population": 1000
    },
    {
        "location": [
            56.85930137734443,
            41.29006651583605
        ],
        "population": 1000
    },
    {
        "location": [
            56.75932600260067,
            41.347793877564435
        ],
        "population": 1000
    },
    {
        "location": [
            56.626154712071525,
            41.35940646375414
        ],
        "population": 1000
    },
    {
        "location": [
            56.49298342154238,
            41.371019049943854
        ],
        "population": 1000
    },
    {
        "location": [
            56.3814808393302,
            41.414227943407376
        ],
        "population": 1000
    },
    {
        "location": [
            56.29205194991043,
            41.48962367375726
        ],
        "population": 1000
    },
    {
        "location": [
            56.202623060490644,
            41.56501940410715
        ],
        "population": 1000
    },
    {
        "location": [
            56.113194171070866,
            41.64041513445703
        ],
        "population": 1000
    },
    {
        "location": [
            56.077860116099835,
            41.73018793290152
        ],
        "population": 1000
    },
    {
        "location": [
            56.08431435091816,
            41.83106702446958
        ],
        "population": 1000
    },
    {
        "location": [
            56.0907685857365,
            41.93194611603764
        ],
        "population": 1000
    },
    {
        "location": [
            56.092669149450444,
            42.032629593073175
        ],
        "population": 1000
    },
    {
        "location": [
            56.0706282544639,
            42.132284603813154
        ],
        "population": 1000
    },
    {
        "location": [
            56.04858735947735,
            42.23193961455314
        ],
        "population": 1000
    },
    {
        "location": [
            56.02654646449081,
            42.33159462529312
        ],
        "population": 1000
    },
    {
        "location": [
            56.00450556950427,
            42.43124963603311
        ],
        "population": 1000
    },
    {
        "location": [
            55.98246467451772,
            42.53090464677309
        ],
        "population": 1000
    },
    {
        "location": [
            55.960423779531176,
            42.630559657513075
        ],
        "population": 1000
    },
    {
        "location": [
            55.93838288454464,
            42.73021466825306
        ],
        "population": 1000
    },
    {
        "location": [
            55.91652170017701,
            42.829894216350446
        ],
        "population": 1000
    },
    {
        "location": [
            55.89545444776279,
            42.92968216645667
        ],
        "population": 1000
    },
    {
        "location": [
            55.874387195348575,
            43.02947011656289
        ],
        "population": 1000
    },
    {
        "location": [
            55.853319942934355,
            43.12925806666912
        ],
        "population": 1000
    },
    {
        "location": [
            55.832252690520136,
            43.22904601677534
        ],
        "population": 1000
    },
    {
        "location": [
            55.81118543810592,
            43.32883396688156
        ],
        "population": 1000
    },
    {
        "location": [
            55.7901181856917,
            43.42862191698779
        ],
        "population": 1000
    },
    {
        "location": [
            55.76905093327749,
            43.528409867094005
        ],
        "population": 1000
    },
    {
        "location": [
            55.74798368086327,
            43.62819781720023
        ],
        "population": 1000
    },
    {
        "location": [
            55.7313701980878,
            43.728427533512686
        ],
        "population": 1000
    },
    {
        "location": [
            55.71560026902591,
            43.82874092131112
        ],
        "population": 1000
    },
    {
        "location": [
            55.69983033996403,
            43.92905430910955
        ],
        "population": 1000
    },
    {
        "location": [
            55.68406041090214,
            44.029367696907975
        ],
        "population": 1000
    },
    {
        "location": [
            55.66829048184025,
            44.129681084706405
        ],
        "population": 1000
    },
    {
        "location": [
            55.65252055277836,
            44.229994472504835
        ],
        "population": 1000
    },
    {
        "location": [
            55.63675062371647,
            44.330307860303265
        ],
        "population": 1000
    },
    {
        "location": [
            55.62098069465459,
            44.430621248101694
        ],
        "population": 1000
    },
    {
        "location": [
            55.6052107655927,
            44.53093463590012
        ],
        "population": 1000
    },
    {
        "location": [
            55.58944083653081,
            44.631248023698554
        ],
        "population": 1000
    },
    {
        "location": [
            55.57367090746892,
            44.731561411496976
        ],
        "population": 1000
    }
]